serviceboot/__init__.py
serviceboot/build_docker.py
serviceboot/build_zip.py
serviceboot/command.py
serviceboot/compile_python.py
serviceboot/config_client.py
serviceboot/consul_client.py
serviceboot/oauth_client.py
serviceboot/onboarding.py
serviceboot/request_info.py
serviceboot/serviceboot.py
serviceboot/token_service.py
serviceboot-2.1.11.dist-info/METADATA
serviceboot-2.1.11.dist-info/WHEEL
serviceboot-2.1.11.dist-info/entry_points.txt
serviceboot-2.1.11.dist-info/top_level.txt
serviceboot-2.1.11.dist-info/RECORD
