Metadata-Version: 2.1
Name: serviceboot
Version: 2.1.11
Summary: ServiceBoot云原生微服务引擎
Home-page: https://openi.pcl.ac.cn/cubepy/serviceboot
Author: cubeai
Author-email: cubeai@163.com
License: Apache License 2.0
Keywords: ServiceBoot Web-framework micro-service cloud-native Web框架 云原生 微服务
Platform: UNKNOWN
Classifier: Development Status :: 4 - Beta
Classifier: Intended Audience :: Developers
Classifier: Intended Audience :: Science/Research
Classifier: Programming Language :: Python :: 3
Classifier: Programming Language :: Python :: 3.5
Classifier: Programming Language :: Python :: 3.6
Classifier: Programming Language :: Python :: 3.7
Classifier: Programming Language :: Python :: 3.8
Classifier: Programming Language :: Python :: 3.9
Classifier: License :: OSI Approved :: Apache Software License
Requires-Python: >=3.5
Requires-Dist: cython (==0.29.21)
Requires-Dist: requests
Requires-Dist: tornado (>=6.0.4)
Requires-Dist: pyyaml (>=5.3.1)
Requires-Dist: python-jwt (==3.2.6)
Requires-Dist: python-consul (==1.1.0)
